webhook_to_fedora_messaging_messages/__init__.py
webhook_to_fedora_messaging_messages/base.py
webhook_to_fedora_messaging_messages/discourse/__init__.py
webhook_to_fedora_messaging_messages/discourse/v1.py
webhook_to_fedora_messaging_messages/forgejo/__init__.py
webhook_to_fedora_messaging_messages/forgejo/utils.py
webhook_to_fedora_messaging_messages/forgejo/v1.py
webhook_to_fedora_messaging_messages/github/__init__.py
webhook_to_fedora_messaging_messages/github/utils.py
webhook_to_fedora_messaging_messages/github/v1.py
webhook_to_fedora_messaging_messages/gitlab/__init__.py
webhook_to_fedora_messaging_messages/gitlab/utils.py
webhook_to_fedora_messaging_messages/gitlab/v1.py
webhook_to_fedora_messaging_messages/py.typed
webhook_to_fedora_messaging_messages-1.4.1.dist-info/METADATA
webhook_to_fedora_messaging_messages-1.4.1.dist-info/WHEEL
webhook_to_fedora_messaging_messages-1.4.1.dist-info/entry_points.txt
webhook_to_fedora_messaging_messages-1.4.1.dist-info/licenses/LICENSES/LGPL-3.0-or-later.txt
webhook_to_fedora_messaging_messages-1.4.1.dist-info/RECORD
