Metadata-Version: 2.4
Name: webhook-to-fedora-messaging-messages
Version: 1.4.1
Summary: A schema package for messages sent by Webhook To Fedora Messaging
License: LGPL-3.0-or-later
License-File: LICENSES/LGPL-3.0-or-later.txt
Keywords: fedora-messaging
Author: Fedora Infrastructure Team
Author-email: infrastructure@lists.fedoraproject.org
Requires-Python: >=3.9,<4.0
Classifier: Development Status :: 5 - Production/Stable
Classifier: Intended Audience :: System Administrators
Classifier: License :: OSI Approved :: GNU Lesser General Public License v3 or later (LGPLv3+)
Classifier: Operating System :: POSIX :: Linux
Classifier: Programming Language :: Python :: 3
Classifier: Programming Language :: Python :: 3.9
Classifier: Programming Language :: Python :: 3.10
Classifier: Programming Language :: Python :: 3.11
Classifier: Programming Language :: Python :: 3.12
Classifier: Programming Language :: Python :: 3.13
Classifier: Programming Language :: Python :: 3.14
Classifier: Topic :: Communications
Classifier: Topic :: Software Development :: Libraries :: Python Modules
Requires-Dist: fedora-messaging (>=3.8.0,<4.0.0)
Project-URL: Homepage, http://github.com/fedora-infra/webhook-to-fedora-messaging-messages
Project-URL: Repository, http://github.com/fedora-infra/webhook-to-fedora-messaging-messages
